{
  "updated": "2026-03-31",
  "fetched_at": "2026-03-31T06:09:25.678435Z",
  "live_count": 16,
  "total_count": 21,
  "wti_price": 102.7,
  "brent_price": null,
  "lme_zinc": 3159,
  "lme_copper": 12225,
  "data_sources": {
    "primary": "commodities-api.com",
    "wti_source": "yahoo-finance",
    "zinc_source": "metals-dev",
    "copper_source": "metals-dev"
  },
  "commodities": {
    "1": {
      "price": 4553.44,
      "name": "Epoxy Resin (DGEBA)",
      "source": "proxy:wti(yahoo-finance)",
      "live": true
    },
    "2": {
      "price": 3589.18,
      "name": "Polyurethane Polyol",
      "source": "proxy:wti(yahoo-finance)",
      "live": true
    },
    "3": {
      "price": 2805.15,
      "name": "Alkyd Resin (long oil)",
      "source": "proxy:wti(yahoo-finance)",
      "live": true
    },
    "4": {
      "price": 3857.03,
      "name": "Acrylic Copolymer (SPC)",
      "source": "proxy:wti(yahoo-finance)",
      "live": true
    },
    "5": {
      "price": 2050,
      "name": "Rosin (WW grade)",
      "source": "hardcoded",
      "live": false
    },
    "6": {
      "price": 3415.79,
      "name": "Titanium Dioxide (rutile)",
      "source": "proxy:wti(yahoo-finance)",
      "live": true
    },
    "7": {
      "price": 4106.7,
      "name": "Zinc Dust (fine)",
      "source": "lme-zinc(metals-dev)",
      "live": true
    },
    "8": {
      "price": 15198.12,
      "name": "Cuprous Oxide (Cu2O)",
      "source": "lme-copper(metals-dev)",
      "live": true
    },
    "9": {
      "price": 1340,
      "name": "Iron Oxide (red/yellow)",
      "source": "hardcoded",
      "live": false
    },
    "10": {
      "price": 2792.56,
      "name": "Zinc Phosphate",
      "source": "lme-zinc(metals-dev)",
      "live": true
    },
    "11": {
      "price": 298,
      "name": "Extenders (CaCO3/barytes)",
      "source": "hardcoded",
      "live": false
    },
    "12": {
      "price": 1587.79,
      "name": "Xylene (mixed)",
      "source": "proxy:wti(yahoo-finance)",
      "live": true
    },
    "13": {
      "price": 2020.82,
      "name": "MEK",
      "source": "proxy:wti(yahoo-finance)",
      "live": true
    },
    "14": {
      "price": 2054.13,
      "name": "Butyl Acetate",
      "source": "proxy:wti(yahoo-finance)",
      "live": true
    },
    "15": {
      "price": 5820.59,
      "name": "Isocyanate Hardener (HDI)",
      "source": "proxy:wti(yahoo-finance)",
      "live": true
    },
    "16": {
      "price": 5100,
      "name": "Rheology Modifiers",
      "source": "hardcoded",
      "live": false
    },
    "17": {
      "price": 9545.0,
      "name": "Co-Biocides (Zineb/ZPT)",
      "source": "lme-zinc(metals-dev)",
      "live": true
    },
    "18": {
      "price": 100.06,
      "name": "Steel Drums & Cans",
      "source": "bls-ppi",
      "live": true
    },
    "19": {
      "price": 195,
      "name": "Freight & Shipping",
      "source": "hardcoded",
      "live": false
    },
    "20": {
      "price": 158.0,
      "name": "Industrial Energy",
      "source": "wti-energy(yahoo-finance)",
      "live": true
    },
    "21": {
      "price": 2.11,
      "name": "Manufacturing Labour",
      "source": "bls-eci",
      "live": true
    }
  }
}